PyArtist/__init__.py
PyArtist-0.5.1.dist-info/METADATA
PyArtist-0.5.1.dist-info/RECORD
PyArtist-0.5.1.dist-info/WHEEL
PyArtist-0.5.1.dist-info/top_level.txt
