Metadata-Version: 2.1
Name: PyArtist
Version: 0.5.1
Summary: A Python library for Python-learners to draw pictures by "turtle"
Home-page: https://github.com/keyan231/Pyartist
Author: Guo Keyan
Author-email: mail@guokeyan.com
Maintainer: Guo Keyan
Maintainer-email: mail@guokeyan.com
License: BSD License
Platform: all
Classifier: Development Status :: 4 - Beta
Classifier: Operating System :: OS Independent
Classifier: Intended Audience :: Developers
Classifier: License :: OSI Approved :: BSD License
Classifier: Programming Language :: Python
Classifier: Programming Language :: Python :: Implementation
Classifier: Programming Language :: Python :: 3
Classifier: Programming Language :: Python :: 3.4
Classifier: Programming Language :: Python :: 3.5
Classifier: Programming Language :: Python :: 3.6
Classifier: Topic :: Software Development :: Libraries
